icsneopy-1.1.0.dist-info/RECORD
icsneopy-1.1.0.dist-info/WHEEL
icsneopy-1.1.0.dist-info/METADATA
icsneopy-1.1.0.dist-info/licenses/LICENSE
include/libredxx/libredxx.h
lib/libredxx.a
lib/cmake/libredxx/libredxxConfig-release.cmake
lib/cmake/libredxx/libredxxConfig.cmake
icsneopy/__init__.py
icsneopy/icsneopy.cpython-314t-darwin.so
icsneopy/py.typed
icsneopy/icsneopy.pyi
