Metadata-Version: 2.2
Name: icsneopy
Version: 1.1.0
Author: Intrepid Control Systems, Inc.
Maintainer-Email: Kyle Schwarz <kschwarz@intrepidcs.com>
License: Copyright (c) 2018-2025 Intrepid Control Systems, Inc.
Classifier: Development Status :: 5 - Production/Stable
Classifier: Intended Audience :: Developers
Classifier: Programming Language :: C
Classifier: Programming Language :: Python
Classifier: Programming Language :: Python :: 3
Classifier: Programming Language :: Python :: 3.9
Classifier: Programming Language :: Python :: 3.10
Classifier: Programming Language :: Python :: 3.11
Classifier: Programming Language :: Python :: 3.12
Classifier: Programming Language :: Python :: 3.13
Classifier: Programming Language :: Python :: 3 :: Only
Classifier: Programming Language :: Python :: Implementation :: CPython
Classifier: Operating System :: Microsoft :: Windows
Classifier: Operating System :: POSIX
Classifier: Operating System :: Unix
Classifier: Operating System :: MacOS
Project-URL: homepage, https://github.com/intrepidcs/libicsneo
Project-URL: documentation, https://libicsneo.readthedocs.io
Project-URL: source, https://github.com/intrepidcs/libicsneo
Project-URL: tracker, https://github.com/intrepidcs/libicsneo/issues
Requires-Python: >=3.9
